scinference/__init__.py
scinference/conformal.py
scinference/core.py
scinference/estimators.py
scinference/ttest.py
scinference-0.1.0.dist-info/METADATA
scinference-0.1.0.dist-info/WHEEL
scinference-0.1.0.dist-info/top_level.txt
scinference-0.1.0.dist-info/RECORD
