Metadata-Version: 2.4
Name: scinference
Version: 0.1.0
Summary: Inference methods for synthetic control and related methods
Author-email: Kaspar Wuthrich <kwuthrich@ucsd.edu>
Maintainer: Anzony Quispe
License: GPL-3.0
Project-URL: Homepage, https://github.com/anzonyquispe/scinference
Project-URL: Repository, https://github.com/anzonyquispe/scinference
Keywords: synthetic control,causal inference,conformal inference,econometrics
Classifier: Development Status :: 4 - Beta
Classifier: Intended Audience :: Science/Research
Classifier: License :: OSI Approved :: GNU General Public License v3 (GPLv3)
Classifier: Operating System :: OS Independent
Classifier: Programming Language :: Python :: 3
Classifier: Programming Language :: Python :: 3.8
Classifier: Programming Language :: Python :: 3.9
Classifier: Programming Language :: Python :: 3.10
Classifier: Programming Language :: Python :: 3.11
Classifier: Programming Language :: Python :: 3.12
Classifier: Topic :: Scientific/Engineering :: Mathematics
Requires-Python: >=3.8
Requires-Dist: numpy>=1.20.0
Requires-Dist: scipy>=1.7.0
Requires-Dist: cvxpy>=1.2.0
Provides-Extra: dev
Requires-Dist: pytest>=7.0.0; extra == "dev"
Requires-Dist: pytest-cov>=4.0.0; extra == "dev"
Requires-Dist: pandas>=1.3.0; extra == "dev"
